{
  "schema_version": "1.0",
  "id": "north-korea/pyongyang",
  "city": "Pyongyang",
  "country": "North Korea",
  "country_code": "KP",
  "coordinates": {
    "lat": 39.02,
    "lng": 125.75
  },
  "metrics": {
    "home_price_1bed_usd": {
      "value": 85000,
      "unit": "USD",
      "as_of": "2026-06",
      "sources": [
        "model_estimate"
      ],
      "confidence": "low",
      "method": "regional-comparable estimate",
      "notes": "Pyongyang apartment market reports and black-market price references, scaled from scarce city-centre data and regional comparables"
    },
    "home_price_2bed_usd": {
      "value": 125000,
      "unit": "USD",
      "as_of": "2026-06",
      "sources": [
        "model_estimate"
      ],
      "confidence": "low",
      "method": "regional-comparable estimate",
      "notes": "Pyongyang apartment market reports and black-market price references, scaled from scarce city-centre data and regional comparables"
    },
    "home_price_3bed_usd": {
      "value": 170000,
      "unit": "USD",
      "as_of": "2026-06",
      "sources": [
        "model_estimate"
      ],
      "confidence": "low",
      "method": "regional-comparable estimate",
      "notes": "Pyongyang apartment market reports and black-market price references, scaled from scarce city-centre data and regional comparables"
    },
    "income_tax_effective_low_pct": {
      "value": 0.0,
      "unit": "pct",
      "as_of": "2026-06",
      "sources": [
        "web"
      ],
      "confidence": "medium",
      "method": "effective rate at $30k/$75k/$150k gross (single filer)",
      "notes": "Effective income tax + employee social contributions, single filer; national rate"
    },
    "income_tax_effective_mid_pct": {
      "value": 0.0,
      "unit": "pct",
      "as_of": "2026-06",
      "sources": [
        "web"
      ],
      "confidence": "medium",
      "method": "effective rate at $30k/$75k/$150k gross (single filer)",
      "notes": "Effective income tax + employee social contributions, single filer; national rate"
    },
    "income_tax_effective_high_pct": {
      "value": 0.0,
      "unit": "pct",
      "as_of": "2026-06",
      "sources": [
        "web"
      ],
      "confidence": "medium",
      "method": "effective rate at $30k/$75k/$150k gross (single filer)",
      "notes": "Effective income tax + employee social contributions, single filer; national rate"
    },
    "air_quality_pm25_ugm3": {
      "value": 47.2,
      "unit": "ugm3",
      "as_of": "2026-07",
      "sources": [
        "web"
      ],
      "confidence": "medium",
      "method": "annual mean PM2.5 (WHO/IQAir/national monitoring)",
      "notes": "Annual mean PM2.5; WHO guideline is 5 µg/m³"
    }
  },
  "provenance": {
    "compiled_by": "hugo-capitals-2026-06",
    "compiled_at": "2026-06-08",
    "status": "published"
  }
}
