{
  "schema_version": "1.0",
  "id": "iraq/baghdad",
  "city": "Baghdad",
  "country": "Iraq",
  "country_code": "IQ",
  "coordinates": {
    "lat": 33.33,
    "lng": 44.4
  },
  "metrics": {
    "home_price_1bed_usd": {
      "value": 68000,
      "unit": "USD",
      "as_of": "2026-06",
      "sources": [
        "model_estimate"
      ],
      "confidence": "low",
      "method": "regional-comparable estimate",
      "notes": "Numbeo city-centre price per m² for Baghdad scaled by typical 1/2/3-bedroom sizes and cross-checked with regional Iraq listings"
    },
    "home_price_2bed_usd": {
      "value": 115000,
      "unit": "USD",
      "as_of": "2026-06",
      "sources": [
        "model_estimate"
      ],
      "confidence": "low",
      "method": "regional-comparable estimate",
      "notes": "Numbeo city-centre price per m² for Baghdad scaled by typical 1/2/3-bedroom sizes and cross-checked with regional Iraq listings"
    },
    "home_price_3bed_usd": {
      "value": 155000,
      "unit": "USD",
      "as_of": "2026-06",
      "sources": [
        "model_estimate"
      ],
      "confidence": "low",
      "method": "regional-comparable estimate",
      "notes": "Numbeo city-centre price per m² for Baghdad scaled by typical 1/2/3-bedroom sizes and cross-checked with regional Iraq listings"
    }
  },
  "provenance": {
    "compiled_by": "hugo-capitals-2026-06",
    "compiled_at": "2026-06-08",
    "status": "published"
  }
}
