{
  "schema_version": "1.0",
  "id": "united-states/orlando",
  "city": "Orlando",
  "country": "United States",
  "country_code": "US",
  "metrics": {
    "home_price_1bed_usd": {
      "value": 163000,
      "unit": "USD",
      "as_of": "2026-05",
      "sources": [
        "globalpropertyguide",
        "numbeo",
        "web"
      ],
      "method": "cross-source-median",
      "confidence": "medium"
    },
    "home_price_2bed_usd": {
      "value": 219000,
      "unit": "USD",
      "as_of": "2026-05",
      "sources": [
        "globalpropertyguide",
        "numbeo",
        "web"
      ],
      "method": "cross-source-median",
      "confidence": "medium"
    },
    "home_price_3bed_usd": {
      "value": 375000,
      "unit": "USD",
      "as_of": "2026-05",
      "sources": [
        "globalpropertyguide",
        "numbeo",
        "web"
      ],
      "method": "cross-source-median",
      "confidence": "medium"
    },
    "cost_of_living_index": {
      "value": 69.0,
      "unit": "index_numbeo_nyc100",
      "as_of": "2026-06",
      "sources": [
        "numbeo"
      ],
      "confidence": "medium",
      "notes": "Numbeo Cost of Living Index, excl. rent, NYC=100"
    },
    "local_purchasing_power_index": {
      "value": 141.5,
      "unit": "index_numbeo_nyc100",
      "as_of": "2026-06",
      "sources": [
        "numbeo"
      ],
      "confidence": "medium",
      "notes": "Numbeo Local Purchasing Power Index, NYC=100"
    }
  },
  "provenance": {
    "compiled_by": "starter-2026.1",
    "compiled_at": "2026-05-31",
    "status": "published"
  },
  "coordinates": {
    "lat": 28.54212,
    "lng": -81.37905
  },
  "media": {
    "photo_ids": [
      "4NUCd1ldaBY"
    ],
    "hero": {
      "url": "https://images.unsplash.com/photo-1758464642918-47f7d0364396?crop=entropy&cs=tinysrgb&fit=max&fm=jpg&ixid=M3w2OTEyOTF8MHwxfGFsbHx8fHx8fHx8fDE3NjM3MjY4MTF8&ixlib=rb-4.1.0&q=80&w=1600",
      "title": "Chromatic Dome by the Waterfront: Palm-Lined Skyline Against Modern Towers",
      "photographer": "𝕡𝕒𝕨𝕤 𝕒𝕟𝕕 𝕡𝕣𝕚𝕟𝕥𝕤",
      "username": "paws_and_prints",
      "ss_url": "https://www.sampleshots.com/photos/4NUCd1ldaBY/",
      "source": "unsplash",
      "license": "Unsplash License"
    }
  },
  "airports": [
    {
      "iata": "MCO",
      "icao": "KMCO",
      "name": "Orlando International Airport",
      "type": "large_airport",
      "distance_km": 14,
      "destinations": 225,
      "airlines": 76,
      "url": "https://www.airportroutes.com/airports/KMCO/"
    },
    {
      "iata": "SFB",
      "icao": "KSFB",
      "name": "Orlando Sanford International Airport",
      "type": "large_airport",
      "distance_km": 30,
      "destinations": 162,
      "airlines": 18,
      "url": "https://www.airportroutes.com/airports/KSFB/"
    },
    {
      "iata": "TPA",
      "icao": "KTPA",
      "name": "Tampa International Airport",
      "type": "large_airport",
      "distance_km": 129,
      "destinations": 114,
      "airlines": 39,
      "url": "https://www.airportroutes.com/airports/KTPA/"
    }
  ]
}
