{
  "schema_version": "1.0",
  "id": "bangladesh/dhaka",
  "city": "Dhaka",
  "country": "Bangladesh",
  "country_code": "BD",
  "coordinates": {
    "lat": 23.72,
    "lng": 90.4
  },
  "metrics": {
    "home_price_1bed_usd": {
      "value": 70000,
      "unit": "USD",
      "as_of": "2026-06",
      "sources": [
        "web"
      ],
      "confidence": "medium",
      "method": "cross-source web research (Numbeo/GPG/listings)",
      "notes": "Numbeo city-centre USD/sqm for Dhaka plus local per-sqft ranges in Gulshan/Banani/Baridhara/Dhanmondi converted at ~120 BDT/USD and typical 1BR~55sqm, 2BR~95sqm"
    },
    "home_price_2bed_usd": {
      "value": 110000,
      "unit": "USD",
      "as_of": "2026-06",
      "sources": [
        "web"
      ],
      "confidence": "medium",
      "method": "cross-source web research (Numbeo/GPG/listings)",
      "notes": "Numbeo city-centre USD/sqm for Dhaka plus local per-sqft ranges in Gulshan/Banani/Baridhara/Dhanmondi converted at ~120 BDT/USD and typical 1BR~55sqm, 2BR~95sqm"
    },
    "home_price_3bed_usd": {
      "value": 150000,
      "unit": "USD",
      "as_of": "2026-06",
      "sources": [
        "web"
      ],
      "confidence": "medium",
      "method": "cross-source web research (Numbeo/GPG/listings)",
      "notes": "Numbeo city-centre USD/sqm for Dhaka plus local per-sqft ranges in Gulshan/Banani/Baridhara/Dhanmondi converted at ~120 BDT/USD and typical 1BR~55sqm, 2BR~95sqm"
    },
    "cost_of_living_index": {
      "value": 25.3,
      "unit": "index_numbeo_nyc100",
      "as_of": "2026-06",
      "sources": [
        "numbeo"
      ],
      "confidence": "medium",
      "notes": "Numbeo Cost of Living Index, excl. rent, NYC=100"
    },
    "local_purchasing_power_index": {
      "value": 39.3,
      "unit": "index_numbeo_nyc100",
      "as_of": "2026-06",
      "sources": [
        "numbeo"
      ],
      "confidence": "medium",
      "notes": "Numbeo Local Purchasing Power Index, NYC=100"
    },
    "rent_1bed_usd_month": {
      "value": 95,
      "unit": "USD_per_month",
      "as_of": "2026-06",
      "sources": [
        "numbeo"
      ],
      "confidence": "medium",
      "notes": "Avg monthly rent, 1-bed city centre"
    },
    "rent_3bed_usd_month": {
      "value": 222,
      "unit": "USD_per_month",
      "as_of": "2026-06",
      "sources": [
        "numbeo"
      ],
      "confidence": "medium",
      "notes": "Avg monthly rent, 3-bed city centre"
    },
    "price_to_rent_ratio": {
      "value": 56.3,
      "unit": "ratio",
      "as_of": "2026-06",
      "sources": [
        "model_estimate"
      ],
      "confidence": "medium",
      "method": "home_price_3bed_usd / (12 * rent_3bed_usd_month)",
      "notes": "Years of 3-bed rent to equal the 3-bed purchase price"
    }
  },
  "provenance": {
    "compiled_by": "hugo-capitals-2026-06",
    "compiled_at": "2026-06-08",
    "status": "published"
  }
}
